PyIntruder.py
PyIntruder-0.1.4.data/scripts/PyIntruder.py
PyIntruder-0.1.4.data/scripts/pyintruder
PyIntruder-0.1.4.dist-info/DESCRIPTION.rst
PyIntruder-0.1.4.dist-info/METADATA
PyIntruder-0.1.4.dist-info/RECORD
PyIntruder-0.1.4.dist-info/WHEEL
PyIntruder-0.1.4.dist-info/metadata.json
PyIntruder-0.1.4.dist-info/top_level.txt
