Metadata-Version: 2.0
Name: PyIntruder
Version: 0.1.4
Summary: Command line URL fuzzer
Home-page: https://github.com/sirpsycho/PyIntruder
Author: sirpsycho
Author-email: UNKNOWN
License: MIT
Keywords: pyintruder,http,fuzzer,url,scan
Platform: UNKNOWN
Classifier: Development Status :: 3 - Alpha
Classifier: License :: OSI Approved :: MIT License
Classifier: Programming Language :: Python
Classifier: Programming Language :: Python :: 2
Classifier: Programming Language :: Python :: 3
Requires-Dist: requests (>=2.12.4)
